age.py
python_age-0.1.0.dist-info/METADATA
python_age-0.1.0.dist-info/WHEEL
python_age-0.1.0.dist-info/entry_points.txt
python_age-0.1.0.dist-info/top_level.txt
python_age-0.1.0.dist-info/RECORD
