Metadata-Version: 2.4
Name: python-age
Version: 0.1.0
Summary: Python implementation of the age (Actually Good Encryption) v1 file format
Author: Dennis Vink
License: BSD-3-Clause
Project-URL: Homepage, https://github.com/dennisvink/python-age
Project-URL: Repository, https://github.com/dennisvink/python-age
Project-URL: Issues, https://github.com/dennisvink/python-age/issues
Classifier: Development Status :: 3 - Alpha
Classifier: Intended Audience :: Developers
Classifier: License :: OSI Approved :: BSD License
Classifier: Programming Language :: Python :: 3
Classifier: Programming Language :: Python :: 3 :: Only
Classifier: Programming Language :: Python :: 3.9
Classifier: Programming Language :: Python :: 3.10
Classifier: Programming Language :: Python :: 3.11
Classifier: Programming Language :: Python :: 3.12
Classifier: Topic :: Security :: Cryptography
Requires-Python: >=3.9
Requires-Dist: cryptography>=41.0.0
